timefhuman/__init__.py
timefhuman/grammar.lark
timefhuman/main.py
timefhuman/renderers.py
timefhuman/utils.py
timefhuman-0.1.4.dist-info/licenses/LICENSE
timefhuman-0.1.4.dist-info/METADATA
timefhuman-0.1.4.dist-info/WHEEL
timefhuman-0.1.4.dist-info/top_level.txt
timefhuman-0.1.4.dist-info/RECORD
