Metadata-Version: 2.4
Name: timefhuman
Version: 0.1.4
Summary: Extract datetimes, datetime ranges, and datetime lists from natural language text
Author-email: Alvin Wan <hi@alvinwan.com>
License: Apache-2.0
Project-URL: Homepage, https://github.com/alvinwan/timefhuman
Project-URL: Download, https://github.com/alvinwan/timefhuman/archive/0.1.2.zip
Requires-Python: >=3.6
License-File: LICENSE
Requires-Dist: lark==1.2.2
Requires-Dist: babel==2.16.0
Requires-Dist: pytz==2024.2
Requires-Dist: python-dateutil==2.9.0.post0
Provides-Extra: test
Requires-Dist: pytest==8.3.4; extra == "test"
Requires-Dist: pytest-cov==6.0.0; extra == "test"
Requires-Dist: coverage==7.6.10; extra == "test"
Requires-Dist: coveralls==4.0.1; extra == "test"
Dynamic: license-file
